vault_mgmt/__init__.py
vault_mgmt/auth.py
vault_mgmt/cli.py
vault_mgmt/compare.py
vault_mgmt/manager.py
vault_mgmt/rollout.py
vault_mgmt/sync.py
vault_mgmt-1.1.2.dist-info/licenses/LICENSE
vault_mgmt-1.1.2.dist-info/METADATA
vault_mgmt-1.1.2.dist-info/WHEEL
vault_mgmt-1.1.2.dist-info/entry_points.txt
vault_mgmt-1.1.2.dist-info/top_level.txt
vault_mgmt-1.1.2.dist-info/RECORD
