Metadata-Version: 2.4
Name: vault-mgmt
Version: 1.1.2
Summary: A collection of CLI tools for managing HashiCorp Vault.
Author-email: "Jeremy T. Bouse" <Jeremy.Bouse@UnderGrid.net>
License-Expression: GPL-3.0-only
Classifier: Development Status :: 4 - Beta
Classifier: Programming Language :: Python :: 3
Classifier: Programming Language :: Python :: 3.9
Classifier: Programming Language :: Python :: 3.10
Classifier: Programming Language :: Python :: 3.11
Classifier: Programming Language :: Python :: 3.12
Classifier: Programming Language :: Python :: 3.13
Classifier: Operating System :: POSIX
Classifier: Intended Audience :: System Administrators
Classifier: Intended Audience :: Information Technology
Classifier: Topic :: Utilities
Requires-Python: >=3.9
License-File: LICENSE
Requires-Dist: certifi==2026.1.4
Requires-Dist: charset-normalizer==3.4.4
Requires-Dist: hvac==2.4.0
Requires-Dist: idna==3.11
Requires-Dist: kubernetes==35.0.0
Requires-Dist: PyYAML==6.0.3
Requires-Dist: requests==2.32.5
Requires-Dist: urllib3==2.6.3
Requires-Dist: tqdm==4.67.1
Dynamic: license-file
